account/__init__.py
account/admin.py
account/apps.py
account/models.py
account/tests.py
account/urls.py
account/views.py
account/migrations/__init__.py
account/static/account/css/account.css
account/static/account/js/account.js
account/templates/account/base.html
account/templates/registration/login.html
account/templates/registration/register.html
django_b2t_accounts-0.0.1.dist-info/LICENSE
django_b2t_accounts-0.0.1.dist-info/METADATA
django_b2t_accounts-0.0.1.dist-info/WHEEL
django_b2t_accounts-0.0.1.dist-info/top_level.txt
django_b2t_accounts-0.0.1.dist-info/RECORD
